<?xml version="1.0" encoding="UTF-8"?>
<!DOCTYPE mapper PUBLIC "-//mybatis.org//DTD Mapper 3.0//EN" "http://mybatis.org/dtd/mybatis-3-mapper.dtd">
<mapper namespace="com.pet.lovepet.dao.mapper.UserRoleMapper">
  <resultMap id="BaseResultMap" type="com.pet.lovepet.entity.UserRole">
    <id column="id" jdbcType="VARCHAR" property="id" />
    <result column="create_time" jdbcType="TIMESTAMP" property="createTime" />
    <result column="delete_flag" jdbcType="INTEGER" property="deleteFlag" />
    <result column="update_time" jdbcType="TIMESTAMP" property="updateTime" />
    <result column="role_id" jdbcType="VARCHAR" property="roleId" />
    <result column="user_id" jdbcType="VARCHAR" property="userId" />
  </resultMap>
  <sql id="Base_Column_List">
    <!--
      WARNING - @mbg.generated
      This element is automatically generated by MyBatis Generator, do not modify.
    -->
    id, create_time, delete_flag, update_time, role_id, user_id
  </sql>
  <select id="selectByPrimaryKey" parameterType="java.lang.String" resultMap="BaseResultMap">
    <!--
      WARNING - @mbg.generated
      This element is automatically generated by MyBatis Generator, do not modify.
    -->
    select 
    <include refid="Base_Column_List" />
    from t_user_role
    where id = #{id,jdbcType=VARCHAR}
  </select>
  <delete id="deleteByPrimaryKey" parameterType="java.lang.String">
    <!--
      WARNING - @mbg.generated
      This element is automatically generated by MyBatis Generator, do not modify.
    -->
    delete from t_user_role
    where id = #{id,jdbcType=VARCHAR}
  </delete>
  <insert id="insert" parameterType="com.pet.lovepet.entity.UserRole">
    <!--
      WARNING - @mbg.generated
      This element is automatically generated by MyBatis Generator, do not modify.
    -->
    insert into t_user_role (id, create_by, create_time, 
      del_flag, update_by, update_time, 
      role_id, user_id)
    values (#{id,jdbcType=VARCHAR}, #{createBy,jdbcType=VARCHAR}, #{createTime,jdbcType=TIMESTAMP}, 
      #{delFlag,jdbcType=INTEGER}, #{updateBy,jdbcType=VARCHAR}, #{updateTime,jdbcType=TIMESTAMP}, 
      #{roleId,jdbcType=VARCHAR}, #{userId,jdbcType=VARCHAR})
  </insert>
  <insert id="insertSelective" parameterType="com.pet.lovepet.entity.UserRole">
    <!--
      WARNING - @mbg.generated
      This element is automatically generated by MyBatis Generator, do not modify.
    -->
    insert into t_user_role
    <trim prefix="(" suffix=")" suffixOverrides=",">
      <if test="id != null">
        id,
      </if>
      <if test="createBy != null">
        create_by,
      </if>
      <if test="createTime != null">
        create_time,
      </if>
      <if test="delFlag != null">
        del_flag,
      </if>
      <if test="updateBy != null">
        update_by,
      </if>
      <if test="updateTime != null">
        update_time,
      </if>
      <if test="roleId != null">
        role_id,
      </if>
      <if test="userId != null">
        user_id,
      </if>
    </trim>
    <trim prefix="values (" suffix=")" suffixOverrides=",">
      <if test="id != null">
        #{id,jdbcType=VARCHAR},
      </if>
      <if test="createBy != null">
        #{createBy,jdbcType=VARCHAR},
      </if>
      <if test="createTime != null">
        #{createTime,jdbcType=TIMESTAMP},
      </if>
      <if test="delFlag != null">
        #{delFlag,jdbcType=INTEGER},
      </if>
      <if test="updateBy != null">
        #{updateBy,jdbcType=VARCHAR},
      </if>
      <if test="updateTime != null">
        #{updateTime,jdbcType=TIMESTAMP},
      </if>
      <if test="roleId != null">
        #{roleId,jdbcType=VARCHAR},
      </if>
      <if test="userId != null">
        #{userId,jdbcType=VARCHAR},
      </if>
    </trim>
  </insert>
  <update id="updateByPrimaryKeySelective" parameterType="com.pet.lovepet.entity.UserRole">
    <!--
      WARNING - @mbg.generated
      This element is automatically generated by MyBatis Generator, do not modify.
    -->
    update t_user_role
    <set>
      <if test="createBy != null">
        create_by = #{createBy,jdbcType=VARCHAR},
      </if>
      <if test="createTime != null">
        create_time = #{createTime,jdbcType=TIMESTAMP},
      </if>
      <if test="delFlag != null">
        del_flag = #{delFlag,jdbcType=INTEGER},
      </if>
      <if test="updateBy != null">
        update_by = #{updateBy,jdbcType=VARCHAR},
      </if>
      <if test="updateTime != null">
        update_time = #{updateTime,jdbcType=TIMESTAMP},
      </if>
      <if test="roleId != null">
        role_id = #{roleId,jdbcType=VARCHAR},
      </if>
      <if test="userId != null">
        user_id = #{userId,jdbcType=VARCHAR},
      </if>
    </set>
    where id = #{id,jdbcType=VARCHAR}
  </update>
  <update id="updateByPrimaryKey" parameterType="com.pet.lovepet.entity.UserRole">
    <!--
      WARNING - @mbg.generated
      This element is automatically generated by MyBatis Generator, do not modify.
    -->
    update t_user_role
    set create_by = #{createBy,jdbcType=VARCHAR},
      create_time = #{createTime,jdbcType=TIMESTAMP},
      del_flag = #{delFlag,jdbcType=INTEGER},
      update_by = #{updateBy,jdbcType=VARCHAR},
      update_time = #{updateTime,jdbcType=TIMESTAMP},
      role_id = #{roleId,jdbcType=VARCHAR},
      user_id = #{userId,jdbcType=VARCHAR}
    where id = #{id,jdbcType=VARCHAR}
  </update>
</mapper>